ta_py/__init__.py
ta_py/ta.py
ta_py-1.5.2.dist-info/LICENSE
ta_py-1.5.2.dist-info/METADATA
ta_py-1.5.2.dist-info/WHEEL
ta_py-1.5.2.dist-info/top_level.txt
ta_py-1.5.2.dist-info/RECORD
