Metadata-Version: 2.1
Name: ta-py
Version: 1.5.2
Summary: ta.py is a Python package for dealing with financial technical analysis
Home-page: https://github.com/Bitvested/ta.py
Author: Nino Kroesen
Author-email: ninokroesen@gmail.com
License: UNKNOWN
Keywords: financial,technical,analysis,ta,simple,weighted,exponential,sma,wma,ema,aroon,rsi,stochastics,macd,atr,vwap,lsma,least,squares,average,kama,variance,correlation,aad,mad,ssd,kmeans,monte,carlo
Platform: UNKNOWN
Classifier: Programming Language :: Python :: 3
Classifier: License :: OSI Approved :: MIT License
Classifier: Operating System :: OS Independent
License-File: LICENSE
